README.md
autoargparse.py
autoargparse.egg-info/PKG-INFO
autoargparse.egg-info/SOURCES.txt
autoargparse.egg-info/dependency_links.txt
autoargparse.egg-info/not-zip-safe
autoargparse.egg-info/top_level.txt
autoargparse-0.1.0.dist-info/LICENSE
autoargparse-0.1.0.dist-info/METADATA
autoargparse-0.1.0.dist-info/WHEEL
autoargparse-0.1.0.dist-info/top_level.txt
autoargparse-0.1.0.dist-info/RECORD
