Metadata-Version: 2.1
Name: autoargparse
Version: 0.1.0
Summary: Make CMD arg-parser easy and simple.
Home-page: https://github.com/gLhookniano/autoargparse
Author: gLhookniano
Author-email: gLhookniano@protonmail.com
License: MIT
Platform: UNKNOWN
Classifier: License :: OSI Approved :: MIT License
Classifier: Programming Language :: Python
Classifier: Programming Language :: Python :: 3
Classifier: Programming Language :: Python :: 3.5
Classifier: Programming Language :: Python :: 3.6
Classifier: Programming Language :: Python :: 3.7
Requires-Python: >=3.5.0
